pyasil/__init__.py
pyasil/integrity.py
pyasiltags-2024.0.0a1.dist-info/LICENSE
pyasiltags-2024.0.0a1.dist-info/METADATA
pyasiltags-2024.0.0a1.dist-info/WHEEL
pyasiltags-2024.0.0a1.dist-info/top_level.txt
pyasiltags-2024.0.0a1.dist-info/RECORD
