Metadata-Version: 2.1
Name: pyasiltags
Version: 2024.0.0a1
Summary: Utilities to deal with safety integrity levels
Author-email: Daniele Faugiana <dan.faugiana@gamil.com>
License: MIT License
Requires-Python: >=3.10
License-File: LICENSE
Provides-Extra: dev
Requires-Dist: ruff; extra == "dev"
Provides-Extra: test
Requires-Dist: pytest; extra == "test"
